iot/lru/cache/__init__.py
iot/lru/cache/_cache.py
iot/lru/cache/_version.py
iot_lru_cache-1.0.0.dist-info/METADATA
iot_lru_cache-1.0.0.dist-info/WHEEL
iot_lru_cache-1.0.0.dist-info/top_level.txt
iot_lru_cache-1.0.0.dist-info/RECORD
